nonebot_plugin_cogvideox/__init__.py
nonebot_plugin_cogvideox/config.py
nonebot_plugin_cogvideox-0.1.4.dist-info/METADATA
nonebot_plugin_cogvideox-0.1.4.dist-info/WHEEL
nonebot_plugin_cogvideox-0.1.4.dist-info/RECORD
