Metadata-Version: 2.1
Name: nonebot-plugin-cogvideox
Version: 0.1.4
Summary: A nonebot plugin for cogvideox
License: MIT
Author: Alpaca
Author-email: alpaca@alpaca.kim
Requires-Python: >=3.8,<4.0
Classifier: License :: OSI Approved :: MIT License
Classifier: Programming Language :: Python :: 3
Classifier: Programming Language :: Python :: 3.8
Classifier: Programming Language :: Python :: 3.9
Classifier: Programming Language :: Python :: 3.10
Classifier: Programming Language :: Python :: 3.11
Classifier: Programming Language :: Python :: 3.12
Classifier: Programming Language :: Python :: 3.13
Requires-Dist: nonebot-adapter-onebot (>=2.2.1,<3.0.0)
Requires-Dist: nonebot2 (>=2.2.0,<3.0.0)
Requires-Dist: zhipuai (>=2.1.5.20250421,<3.0.0.0)
